intent_classifier/__init__.py
intent_classifier/base.py
intent_classifier/dataset.py
intent_classifier/intent.py
intent_classifier/intent_classifier.py
intent_classifier/preprocess.py
intent_classifier/transformer.py
intent_classifier/utils.py
intent_classifier/vectorizer.py
intent_classifier-0.2.1.dist-info/LICENSE
intent_classifier-0.2.1.dist-info/METADATA
intent_classifier-0.2.1.dist-info/WHEEL
intent_classifier-0.2.1.dist-info/top_level.txt
intent_classifier-0.2.1.dist-info/RECORD
