Metadata-Version: 2.1
Name: intent-classifier
Version: 0.2.1
Summary: An Intent Classifier For Chatbot
Home-page: https://github.com/aitrek/intent_classifier
Author: aitrek
Author-email: aitrek.zh@gmail.com
License: MIT
Platform: UNKNOWN
Requires-Dist: numpy
Requires-Dist: scipy
Requires-Dist: PyMySQL
Requires-Dist: scikit-learn (==0.20.3)
